dragnet/__init__.py
dragnet/blocks.cpython-37m-darwin.so
dragnet/compat.py
dragnet/data_processing.py
dragnet/extractor.py
dragnet/lcs.cpython-37m-darwin.so
dragnet/model_training.py
dragnet/util.py
dragnet/features/__init__.py
dragnet/features/_kohlschuetter.cpython-37m-darwin.so
dragnet/features/_readability.cpython-37m-darwin.so
dragnet/features/_weninger.cpython-37m-darwin.so
dragnet/features/css.py
dragnet/features/kohlschuetter.py
dragnet/features/readability.py
dragnet/features/standardized.py
dragnet/features/weninger.py
dragnet/pickled_models/py2_sklearn_0.15.2_0.17.1/kohlschuetter_readability_weninger_comments_block_errors.txt
dragnet/pickled_models/py2_sklearn_0.15.2_0.17.1/kohlschuetter_readability_weninger_comments_content_block_errors.txt
dragnet/pickled_models/py2_sklearn_0.15.2_0.17.1/kohlschuetter_readability_weninger_comments_content_model.pkl.gz
dragnet/pickled_models/py2_sklearn_0.15.2_0.17.1/kohlschuetter_readability_weninger_comments_model.pkl.gz
dragnet/pickled_models/py2_sklearn_0.15.2_0.17.1/kohlschuetter_readability_weninger_content_block_errors.txt
dragnet/pickled_models/py2_sklearn_0.15.2_0.17.1/kohlschuetter_readability_weninger_content_model.pkl.gz
dragnet/pickled_models/py2_sklearn_0.18.0/kohlschuetter_readability_weninger_comments_block_errors.txt
dragnet/pickled_models/py2_sklearn_0.18.0/kohlschuetter_readability_weninger_comments_content_block_errors.txt
dragnet/pickled_models/py2_sklearn_0.18.0/kohlschuetter_readability_weninger_comments_content_model.pkl.gz
dragnet/pickled_models/py2_sklearn_0.18.0/kohlschuetter_readability_weninger_comments_model.pkl.gz
dragnet/pickled_models/py2_sklearn_0.18.0/kohlschuetter_readability_weninger_content_block_errors.txt
dragnet/pickled_models/py2_sklearn_0.18.0/kohlschuetter_readability_weninger_content_model.pkl.gz
dragnet/pickled_models/py3_sklearn_0.15.2_0.17.1/kohlschuetter_readability_weninger_comments_block_errors.txt
dragnet-2.0.4.dist-info/LICENSE
dragnet-2.0.4.dist-info/METADATA
dragnet-2.0.4.dist-info/WHEEL
dragnet-2.0.4.dist-info/top_level.txt
dragnet-2.0.4.dist-info/RECORD
